neo4j/__init__.py
neo4j_connector-1.1.0.dist-info/LICENCE
neo4j_connector-1.1.0.dist-info/METADATA
neo4j_connector-1.1.0.dist-info/WHEEL
neo4j_connector-1.1.0.dist-info/top_level.txt
neo4j_connector-1.1.0.dist-info/RECORD
