Metadata-Version: 2.1
Name: neo4j-connector
Version: 1.1.0
Summary: Connector with single-request transactions for Neo4j 3.0 and above
Home-page: https://github.com/textkernel/neo4j-connector
Author: Jelle Jan Bankert (Textkernel BV)
Author-email: bankert@textkernel.com
License: MIT
Platform: UNKNOWN
Classifier: Intended Audience :: Developers
Classifier: License :: OSI Approved :: MIT License
Classifier: Operating System :: OS Independent
Classifier: Programming Language :: Python :: 3.5
Classifier: Programming Language :: Python :: 3.6
Classifier: Programming Language :: Python :: 3.7
Classifier: Programming Language :: Python :: 3.8
Classifier: Topic :: Database
Classifier: Topic :: Software Development
Classifier: Topic :: Utilities
Requires-Dist: requests (<3.0,>=2.0)
